mongodb_connect/__init__.py
mongodb_connect/mongo_crud.py
dbautomationtool-0.0.3.dist-info/LICENSE
dbautomationtool-0.0.3.dist-info/METADATA
dbautomationtool-0.0.3.dist-info/WHEEL
dbautomationtool-0.0.3.dist-info/top_level.txt
dbautomationtool-0.0.3.dist-info/RECORD
