Metadata-Version: 2.1
Name: dbautomationtool
Version: 0.0.3
Summary: A Python package for connecting with databases.
Home-page: https://github.com/Mohammad Shuaib/mongodb-connector-package
Author: Mohammad Shuaib
Author-email: mohammadshuaib3455@gmail.com
License: MIT
Project-URL: Bug Tracker, https://github.com/Mohammad Shuaib/mongodb-connector-package/issues
Classifier: Programming Language :: Python :: 3.11
Classifier: Operating System :: OS Independent
Requires-Python: >=3.11
License-File: LICENSE
Requires-Dist: ensure==1.0.2
Requires-Dist: py-youtube==1.1.7
Provides-Extra: testing
Requires-Dist: pytest>=7.1.3; extra == "testing"
Requires-Dist: mypy>=1.11.1; extra == "testing"
Requires-Dist: flake8>=6.0.0; extra == "testing"
Requires-Dist: tox>=4.16.0; extra == "testing"
Requires-Dist: black>=24.8.0; extra == "testing"
